QtQmlViewport/Actors.py
QtQmlViewport/Array.py
QtQmlViewport/Camera.py
QtQmlViewport/CustomActors.py
QtQmlViewport/CustomAttribs.py
QtQmlViewport/CustomEffects.py
QtQmlViewport/Effect.py
QtQmlViewport/Geometry.py
QtQmlViewport/Image.py
QtQmlViewport/InFboRenderer.py
QtQmlViewport/Product.py
QtQmlViewport/Table.py
QtQmlViewport/Transforms.py
QtQmlViewport/Viewport.py
QtQmlViewport/__init__.py
QtQmlViewport/interactive.py
QtQmlViewport/linalg.py
QtQmlViewport/utils.py
QtQmlViewport/qml/__init__.py
QtQmlViewport/qml/example.qml
QtQmlViewport/qml/root_MPL.qml
QtQmlViewport/qml/Examples/qmldir
QtQmlViewport/qml/Misc/Utils.js
QtQmlViewport/qml/Misc/qmldir
QtQmlViewport/qml/UI2D/PZQImagePainter.qml
QtQmlViewport/qml/UI2D/SmallCheckBox.qml
QtQmlViewport/qml/UI2D/qmldir
QtQmlViewport/qml/UI3D/qmldir
QtQmlViewport/qml/UI3D/Actors/Actors.qml
QtQmlViewport/qml/UI3D/Actors/Arrow2D.qml
QtQmlViewport/qml/UI3D/Actors/Box.qml
QtQmlViewport/qml/UI3D/Actors/Grid2D.qml
QtQmlViewport/qml/UI3D/Actors/Line.qml
QtQmlViewport/qml/UI3D/Actors/Points.qml
QtQmlViewport/qml/UI3D/Actors/XYZ.qml
QtQmlViewport/qml/UI3D/Effects/AmplitudesProgram.qml
QtQmlViewport/qml/UI3D/Effects/ColorMapProgram.qml
QtQmlViewport/qml/UI3D/Effects/EmissiveProgram.qml
QtQmlViewport/qml/UI3D/Effects/MaterialProgram.qml
QtQmlViewport/qml/UI3D/Effects/PointsColorProgram.qml
QtQmlViewport/qml/backend_qtquick5/__init__.py
QtQmlViewport/qml/backend_qtquick5/backend_qquick5agg.py
QtQmlViewport/qml/backend_qtquick5/MPLBackend/Figure.qml
QtQmlViewport/qml/backend_qtquick5/MPLBackend/FigureWithToolbar.qml
QtQmlViewport/qml/backend_qtquick5/MPLBackend/SubplotTool.qml
QtQmlViewport/qml/backend_qtquick5/MPLBackend/qmldir
QtQmlViewport-0.2.2.dist-info/LICENSE
QtQmlViewport-0.2.2.dist-info/METADATA
QtQmlViewport-0.2.2.dist-info/WHEEL
QtQmlViewport-0.2.2.dist-info/top_level.txt
QtQmlViewport-0.2.2.dist-info/RECORD
