Metadata-Version: 2.1
Name: QtQmlViewport
Version: 0.2.2
Summary: Python QtQml 3D viewer toolkit
Home-page: https://github.com/maxlem/QtQmlViewport
Author: Maxime Lemonnier
License: UNKNOWN
Platform: UNKNOWN
License-File: LICENSE
Requires-Dist: future
Requires-Dist: transforms3d
Requires-Dist: matplotlib
Requires-Dist: numpy
Requires-Dist: opencv-python
Requires-Dist: PyOpenGL
Requires-Dist: PyQt5 (==5.14)
Requires-Dist: PyQtChart (==5.14)
Requires-Dist: pycollada
Requires-Dist: trimesh
Requires-Dist: utm
Requires-Dist: Shapely
Requires-Dist: tqdm
